jobsubmitter/__init__.py
jobsubmitter/job_opts.py
jobsubmitter/jobsubmitter.py
jobsubmitter/system_command.py
jobsubmitter/utils.py
jobsubmitter/scripts/qsub.sh
jobsubmitter-0.1.0.data/scripts/qsub.sh
jobsubmitter-0.1.0.dist-info/DESCRIPTION.rst
jobsubmitter-0.1.0.dist-info/METADATA
jobsubmitter-0.1.0.dist-info/RECORD
jobsubmitter-0.1.0.dist-info/WHEEL
jobsubmitter-0.1.0.dist-info/entry_points.txt
jobsubmitter-0.1.0.dist-info/metadata.json
jobsubmitter-0.1.0.dist-info/top_level.txt
