Metadata-Version: 2.0
Name: jobsubmitter
Version: 0.1.0
Summary: Package for running jobs on Sun Grid Engine (SGE) / PBS / Slurm clusters.
Home-page: https://gitlab.com/ostrokach/jobsubmitter
Author: Alexey Strokach
Author-email: alex.strokach@utoronto.ca
License: MIT
Keywords: jobsubmitter
Platform: UNKNOWN
Classifier: License :: OSI Approved :: MIT License
Classifier: Development Status :: 2 - Pre-Alpha
Classifier: Intended Audience :: Developers
Classifier: Natural Language :: English
Classifier: Programming Language :: Python :: 3.6
Requires-Dist: Click (>=6.0)
